subsy/__init__.py
subsy/meta.py
subsy/readers.py
subsy/subtitle.py
subsy/subtitles.py
subsy/timestamp.py
subsy/writers.py
subsy-1.0.0.dist-info/license.txt
subsy-1.0.0.dist-info/WHEEL
subsy-1.0.0.dist-info/METADATA
subsy-1.0.0.dist-info/RECORD
