Metadata-Version: 2.1
Name: subsy
Version: 1.0.0
Summary: Access to subtitles from various file formats
Keywords: subtitles,.srt,.ass,.ssa,.vtt,.sub
Author: John Hennig
Requires-Python: >=3.6
Classifier: Development Status :: 5 - Production/Stable
Classifier: Programming Language :: Python :: 3
Classifier: Operating System :: OS Independent
Classifier: Topic :: Multimedia :: Sound/Audio :: Speech
Classifier: Intended Audience :: Developers
Classifier: Natural Language :: English
Classifier: License :: OSI Approved :: MIT License
Requires-Dist: srt3
Requires-Dist: aeidon
Requires-Dist: chardet
Requires-Dist: Sphinx ; extra == "docs"
Requires-Dist: Furo ; extra == "docs"
Requires-Dist: MyST-parser ; extra == "docs"
Requires-Dist: CommonMark ; extra == "docs"
Requires-Dist: pyTest ; extra == "test"
Requires-Dist: pyTest-cov ; extra == "test"
Requires-Dist: flake8 ; extra == "test"
Requires-Dist: pyproject-flake8 ; extra == "test"
Project-URL: Documentation, https://subsy.readthedocs.io
Project-URL: Source, https://github.com/john-hen/subsy
Provides-Extra: docs
Provides-Extra: test
